{"Entries":[{"P_Area":"","D_Num":"AM16385","P_Sub":"CATHERINE BAY","P_Code":"2281","P_U_Num":"","C_Date":"2014-04-23","S_Date":"2016-12-20","Area_Type":"","P_S_Name":"QUINN STREET","D_Code":"004","P_H_Num":"LOT 2085, ","P_Price":"265000","P_Purp":"VACANT LAND","SL_Num":""},{"P_Area":"","D_Num":"AM47046","P_Sub":"CATHERINE BAY","P_Code":"2281","P_U_Num":"","C_Date":"2016-04-23","S_Date":"2016-12-16","Area_Type":"","P_S_Name":"QUINN STREET","D_Code":"004","P_H_Num":"LOT 2084, ","P_Price":"270000","P_Purp":"RESIDENCE","SL_Num":""}]}