{"Entries":[{"P_Area":"4.559","D_Num":"8584408","P_Sub":"DARKWOOD","P_Code":"2454","P_U_Num":"","C_Date":"2002-02-11","S_Date":"2002-05-06","Area_Type":"H","P_S_Name":"DARKWOOD RD","D_Code":"149","P_H_Num":"2293","P_Price":"95000","P_Purp":"RESIDENCE","SL_Num":""},{"P_Area":"426.6","D_Num":"AA17306","P_Sub":"DARKWOOD","P_Code":"2454","P_U_Num":"","C_Date":"2003-09-16","S_Date":"2003-09-16","Area_Type":"H","P_S_Name":"DARKWOOD RD","D_Code":"149","P_H_Num":"1824","P_Price":"50000","P_Purp":"VACANT LAND","SL_Num":""},{"P_Area":"80.94","D_Num":"9766266","P_Sub":"DARKWOOD","P_Code":"2454","P_U_Num":"","C_Date":"2003-05-13","S_Date":"2003-06-10","Area_Type":"H","P_S_Name":"DARKWOOD RD","D_Code":"149","P_H_Num":"2410","P_Price":"370000","P_Purp":"RESIDENCE","SL_Num":""},{"P_Area":"426.6","D_Num":"8583019","P_Sub":"DARKWOOD","P_Code":"2454","P_U_Num":"","C_Date":"2002-02-26","S_Date":"2002-05-03","Area_Type":"H","P_S_Name":"DARKWOOD RD","D_Code":"149","P_H_Num":"1824","P_Price":"126000","P_Purp":"RESIDENCE","SL_Num":""},{"P_Area":"426.6","D_Num":"AA788523","P_Sub":"DARKWOOD","P_Code":"2454","P_U_Num":"","C_Date":"2004-05-18","S_Date":"2004-06-29","Area_Type":"H","P_S_Name":"DARKWOOD RD","D_Code":"149","P_H_Num":"1824","P_Price":"195000","P_Purp":"RESIDENCE","SL_Num":""},{"P_Area":"6769.3","D_Num":"AA617547","P_Sub":"DARKWOOD","P_Code":"2454","P_U_Num":"","C_Date":"2004-02-13","S_Date":"2004-02-13","Area_Type":"M","P_S_Name":"DARKWOOD RD","D_Code":"149","P_H_Num":"","P_Price":"5000","P_Purp":"VACANT LAND","SL_Num":""},{"P_Area":"9.876","D_Num":"AB15986","P_Sub":"DARKWOOD","P_Code":"2454","P_U_Num":"","C_Date":"2004-10-08","S_Date":"2004-10-08","Area_Type":"H","P_S_Name":"DARKWOOD RD","D_Code":"149","P_H_Num":"2198","P_Price":"245000","P_Purp":"RESIDENCE","SL_Num":""},{"P_Area":"","D_Num":"AB861714","P_Sub":"DARKWOOD","P_Code":"2454","P_U_Num":"","C_Date":"2005-09-30","S_Date":"2005-09-30","Area_Type":"","P_S_Name":"DARKWOOD RD VIA THORA","D_Code":"149","P_H_Num":"2240","P_Price":"5000","P_Purp":"VACANT LAND","SL_Num":""},{"P_Area":"10.17","D_Num":"AC653179","P_Sub":"DARKWOOD","P_Code":"2454","P_U_Num":"","C_Date":"2006-08-04","S_Date":"2006-09-08","Area_Type":"H","P_S_Name":"DARKWOOD RD","D_Code":"149","P_H_Num":"2196","P_Price":"150000","P_Purp":"RESIDENCE","SL_Num":""},{"P_Area":"9.157","D_Num":"AC598740","P_Sub":"DARKWOOD","P_Code":"2454","P_U_Num":"","C_Date":"2006-08-04","S_Date":"2006-09-01","Area_Type":"H","P_S_Name":"DARKWOOD RD","D_Code":"149","P_H_Num":"2291","P_Price":"220000","P_Purp":"RESIDENCE","SL_Num":""},{"P_Area":"3.823","D_Num":"AE92472","P_Sub":"DARKWOOD","P_Code":"2454","P_U_Num":"","C_Date":"2008-06-20","S_Date":"2008-07-09","Area_Type":"H","P_S_Name":"DARKWOOD RD","D_Code":"149","P_H_Num":"1119","P_Price":"435000","P_Purp":"RESIDENCE","SL_Num":""},{"P_Area":"39.9","D_Num":"AD680418","P_Sub":"DARKWOOD","P_Code":"2454","P_U_Num":"","C_Date":"2007-10-17","S_Date":"2007-12-17","Area_Type":"H","P_S_Name":"DARKWOOD RD","D_Code":"149","P_H_Num":"2287","P_Price":"920000","P_Purp":"RESIDENCE","SL_Num":""},{"P_Area":"6400","D_Num":"AD975281","P_Sub":"DARKWOOD","P_Code":"2454","P_U_Num":"","C_Date":"2008-02-05","S_Date":"2008-03-19","Area_Type":"M","P_S_Name":"DARKWOOD RD","D_Code":"149","P_H_Num":"","P_Price":"7740","P_Purp":"VACANT LAND","SL_Num":""},{"P_Area":"39.53","D_Num":"AD832650","P_Sub":"DARKWOOD","P_Code":"2454","P_U_Num":"","C_Date":"2007-12-19","S_Date":"2008-01-23","Area_Type":"H","P_S_Name":"DARKWOOD RD","D_Code":"149","P_H_Num":"1165","P_Price":"285000","P_Purp":"RESIDENCE","SL_Num":""},{"P_Area":"15.17","D_Num":"AD906336","P_Sub":"DARKWOOD","P_Code":"2454","P_U_Num":"","C_Date":"2008-02-07","S_Date":"2008-03-13","Area_Type":"H","P_S_Name":"DARKWOOD RD","D_Code":"149","P_H_Num":"1159","P_Price":"385000","P_Purp":"RESIDENCE","SL_Num":""},{"P_Area":"426.6","D_Num":"AE828832","P_Sub":"DARKWOOD","P_Code":"2454","P_U_Num":"","C_Date":"2009-05-27","S_Date":"2009-07-07","Area_Type":"H","P_S_Name":"DARKWOOD RD","D_Code":"149","P_H_Num":"1824","P_Price":"192000","P_Purp":"RESIDENCE","SL_Num":""},{"P_Area":"140.5","D_Num":"AF17337","P_Sub":"DARKWOOD","P_Code":"2454","P_U_Num":"","C_Date":"2009-08-18","S_Date":"2009-08-21","Area_Type":"H","P_S_Name":"DARKWOOD RD","D_Code":"149","P_H_Num":"1169","P_Price":"200000","P_Purp":"FARM","SL_Num":""},{"P_Area":"15.38","D_Num":"AF700825","P_Sub":"DARKWOOD","P_Code":"2454","P_U_Num":"","C_Date":"2010-06-29","S_Date":"2010-08-03","Area_Type":"H","P_S_Name":"DARKWOOD RD","D_Code":"149","P_H_Num":"1971","P_Price":"260000","P_Purp":"RESIDENCE","SL_Num":""},{"P_Area":"2.028","D_Num":"AF193283","P_Sub":"DARKWOOD","P_Code":"2454","P_U_Num":"","C_Date":"2009-10-27","S_Date":"2009-12-08","Area_Type":"H","P_S_Name":"DARKWOOD RD","D_Code":"149","P_H_Num":"1476","P_Price":"540000","P_Purp":"RESIDENCE","SL_Num":""},{"P_Area":"9.876","D_Num":"AF788098","P_Sub":"DARKWOOD","P_Code":"2454","P_U_Num":"","C_Date":"2010-08-24","S_Date":"2010-09-17","Area_Type":"H","P_S_Name":"DARKWOOD RD","D_Code":"149","P_H_Num":"2198","P_Price":"260000","P_Purp":"RESIDENCE","SL_Num":""},{"P_Area":"20.97","D_Num":"AG144047","P_Sub":"DARKWOOD","P_Code":"2454","P_U_Num":"","C_Date":"2011-02-15","S_Date":"2011-03-22","Area_Type":"H","P_S_Name":"DARKWOOD RD","D_Code":"149","P_H_Num":"1244","P_Price":"280000","P_Purp":"RESIDENCE","SL_Num":""},{"P_Area":"40.47","D_Num":"AG379327","P_Sub":"DARKWOOD","P_Code":"2454","P_U_Num":"","C_Date":"2010-10-29","S_Date":"2011-07-08","Area_Type":"H","P_S_Name":"DARKWOOD RD","D_Code":"149","P_H_Num":"1169","P_Price":"65000","P_Purp":"VACANT LAND","SL_Num":""},{"P_Area":"426.6","D_Num":"AG621726","P_Sub":"DARKWOOD","P_Code":"2454","P_U_Num":"","C_Date":"2011-08-09","S_Date":"2011-11-09","Area_Type":"H","P_S_Name":"DARKWOOD RD","D_Code":"149","P_H_Num":"1824","P_Price":"210000","P_Purp":"RESIDENCE","SL_Num":""},{"P_Area":"13.24","D_Num":"AG274331","P_Sub":"DARKWOOD","P_Code":"2454","P_U_Num":"","C_Date":"2008-12-24","S_Date":"2011-05-13","Area_Type":"H","P_S_Name":"DARKWOOD RD","D_Code":"149","P_H_Num":"2289","P_Price":"375000","P_Purp":"RESIDENCE","SL_Num":""},{"P_Area":"3035","D_Num":"AG104582","P_Sub":"DARKWOOD","P_Code":"2454","P_U_Num":"","C_Date":"2011-01-24","S_Date":"2011-02-28","Area_Type":"M","P_S_Name":"DARKWOOD RD","D_Code":"149","P_H_Num":"1108","P_Price":"350000","P_Purp":"RESIDENCE","SL_Num":""},{"P_Area":"40.47","D_Num":"AG176209","P_Sub":"DARKWOOD","P_Code":"2454","P_U_Num":"","C_Date":"2011-03-11","S_Date":"2011-04-07","Area_Type":"H","P_S_Name":"DARKWOOD RD","D_Code":"149","P_H_Num":"891","P_Price":"35000","P_Purp":"VACANT LAND","SL_Num":""},{"P_Area":"426.6","D_Num":"AG455528","P_Sub":"DARKWOOD","P_Code":"2454","P_U_Num":"","C_Date":"2011-07-12","S_Date":"2011-08-16","Area_Type":"H","P_S_Name":"DARKWOOD RD","D_Code":"149","P_H_Num":"1824","P_Price":"195000","P_Purp":"RESIDENCE","SL_Num":""},{"P_Area":"17.61","D_Num":"AH294241","P_Sub":"DARKWOOD","P_Code":"2454","P_U_Num":"","C_Date":"2012-08-31","S_Date":"2012-09-28","Area_Type":"H","P_S_Name":"DARKWOOD RD","D_Code":"149","P_H_Num":"1211","P_Price":"320000","P_Purp":"RESIDENCE","SL_Num":""},{"P_Area":"79.83","D_Num":"AH205907","P_Sub":"DARKWOOD","P_Code":"2454","P_U_Num":"","C_Date":"2010-07-15","S_Date":"2012-08-24","Area_Type":"H","P_S_Name":"DARKWOOD RD","D_Code":"149","P_H_Num":"1169","P_Price":"140000","P_Purp":"VACANT LAND","SL_Num":""},{"P_Area":"39.53","D_Num":"AH688733","P_Sub":"DARKWOOD","P_Code":"2454","P_U_Num":"","C_Date":"2013-03-13","S_Date":"2013-04-10","Area_Type":"H","P_S_Name":"DARKWOOD RD","D_Code":"149","P_H_Num":"1165","P_Price":"505000","P_Purp":"RESIDENCE","SL_Num":""},{"P_Area":"15.17","D_Num":"AH556855","P_Sub":"DARKWOOD","P_Code":"2454","P_U_Num":"","C_Date":"2012-12-20","S_Date":"2013-02-04","Area_Type":"H","P_S_Name":"DARKWOOD RD","D_Code":"149","P_H_Num":"1159","P_Price":"425000","P_Purp":"RESIDENCE","SL_Num":""},{"P_Area":"13.24","D_Num":"AH842947","P_Sub":"DARKWOOD","P_Code":"2454","P_U_Num":"","C_Date":"2013-05-21","S_Date":"2013-06-21","Area_Type":"H","P_S_Name":"DARKWOOD RD","D_Code":"149","P_H_Num":"2289","P_Price":"250000","P_Purp":"VACANT LAND","SL_Num":""},{"P_Area":"1.12","D_Num":"AH971005","P_Sub":"DARKWOOD","P_Code":"2454","P_U_Num":"","C_Date":"2013-08-16","S_Date":"2013-08-16","Area_Type":"H","P_S_Name":"DARKWOOD RD","D_Code":"149","P_H_Num":"","P_Price":"3504","P_Purp":"VACANT LAND","SL_Num":""},{"P_Area":"20.23","D_Num":"AI690900","P_Sub":"DARKWOOD","P_Code":"2454","P_U_Num":"","C_Date":"2011-01-27","S_Date":"2014-06-20","Area_Type":"H","P_S_Name":"DARKWOOD RD","D_Code":"149","P_H_Num":"","P_Price":"40000","P_Purp":"VACANT LAND","SL_Num":""},{"P_Area":"40.47","D_Num":"AJ825922","P_Sub":"DARKWOOD","P_Code":"2454","P_U_Num":"","C_Date":"2015-07-23","S_Date":"2015-08-27","Area_Type":"H","P_S_Name":"DARKWOOD RD","D_Code":"149","P_H_Num":"870","P_Price":"430000","P_Purp":"VACANT LAND","SL_Num":""},{"P_Area":"80.94","D_Num":"AK259805","P_Sub":"DARKWOOD","P_Code":"2454","P_U_Num":"","C_Date":"2016-02-19","S_Date":"2016-02-19","Area_Type":"H","P_S_Name":"DARKWOOD RD","D_Code":"149","P_H_Num":"2518","P_Price":"100000","P_Purp":"RESIDENCE","SL_Num":""},{"P_Area":"426.6","D_Num":"AK683754","P_Sub":"DARKWOOD","P_Code":"2454","P_U_Num":"","C_Date":"2016-06-23","S_Date":"2016-08-05","Area_Type":"H","P_S_Name":"DARKWOOD RD","D_Code":"149","P_H_Num":"1824","P_Price":"215000","P_Purp":"RESIDENCE","SL_Num":""},{"P_Area":"97.12","D_Num":"AK739450","P_Sub":"DARKWOOD","P_Code":"2454","P_U_Num":"","C_Date":"2016-07-26","S_Date":"2016-08-30","Area_Type":"H","P_S_Name":"DARKWOOD RD","D_Code":"149","P_H_Num":"924","P_Price":"200000","P_Purp":"RESIDENCE","SL_Num":""},{"P_Area":"10.17","D_Num":"AK811865","P_Sub":"DARKWOOD","P_Code":"2454","P_U_Num":"","C_Date":"2016-08-19","S_Date":"2016-09-23","Area_Type":"H","P_S_Name":"DARKWOOD RD","D_Code":"149","P_H_Num":"2196","P_Price":"440000","P_Purp":"RESIDENCE","SL_Num":""},{"P_Area":"32.68","D_Num":"AM571257","P_Sub":"DARKWOOD","P_Code":"2454","P_U_Num":"","C_Date":"2017-07-14","S_Date":"2017-07-14","Area_Type":"H","P_S_Name":"DARKWOOD RD","D_Code":"149","P_H_Num":"922","P_Price":"160600","P_Purp":"RESIDENCE","SL_Num":""},{"P_Area":"13.86","D_Num":"AM634281","P_Sub":"DARKWOOD","P_Code":"2454","P_U_Num":"","C_Date":"2017-07-14","S_Date":"2017-08-04","Area_Type":"H","P_S_Name":"DARKWOOD RD","D_Code":"149","P_H_Num":"1627","P_Price":"620000","P_Purp":"RESIDENCE","SL_Num":""},{"P_Area":"39.9","D_Num":"AP93707","P_Sub":"DARKWOOD","P_Code":"2454","P_U_Num":"","C_Date":"2019-01-21","S_Date":"2019-02-28","Area_Type":"H","P_S_Name":"DARKWOOD RD","D_Code":"149","P_H_Num":"2287","P_Price":"575000","P_Purp":"RESIDENCE","SL_Num":""},{"P_Area":"10.17","D_Num":"AP154846","P_Sub":"DARKWOOD","P_Code":"2454","P_U_Num":"","C_Date":"2019-02-15","S_Date":"2019-03-29","Area_Type":"H","P_S_Name":"DARKWOOD RD","D_Code":"149","P_H_Num":"2196","P_Price":"560000","P_Purp":"RESIDENCE","SL_Num":""},{"P_Area":"426.6","D_Num":"AQ138458","P_Sub":"DARKWOOD","P_Code":"2454","P_U_Num":"","C_Date":"2020-05-06","S_Date":"2020-05-29","Area_Type":"H","P_S_Name":"DARKWOOD RD","D_Code":"149","P_H_Num":"1824","P_Price":"200000","P_Purp":"VACANT LAND","SL_Num":""}]}