{"Entries":[{"P_Area":"6677","D_Num":"AH419284","P_Sub":"OMADALE","P_Code":"2337","P_U_Num":"","C_Date":"2012-11-01","S_Date":"2012-11-29","Area_Type":"M","P_S_Name":"OMADALE BROOK RD","D_Code":"511","P_H_Num":"148","P_Price":"295000","P_Purp":"RESIDENCE","SL_Num":""},{"P_Area":"807.68","D_Num":"AK139120","P_Sub":"OMADALE","P_Code":"2337","P_U_Num":"","C_Date":"2015-10-30","S_Date":"2015-12-14","Area_Type":"H","P_S_Name":"OMADALE TRL","D_Code":"511","P_H_Num":"","P_Price":"1500000","P_Purp":"FARM","SL_Num":""},{"P_Area":"6677","D_Num":"AK611310","P_Sub":"OMADALE","P_Code":"2337","P_U_Num":"","C_Date":"2016-04-27","S_Date":"2016-06-08","Area_Type":"M","P_S_Name":"OMADALE BROOK RD","D_Code":"511","P_H_Num":"148","P_Price":"250000","P_Purp":"RESIDENCE","SL_Num":""},{"P_Area":"6551","D_Num":"AM917591","P_Sub":"OMADALE","P_Code":"2337","P_U_Num":"","C_Date":"2017-11-22","S_Date":"2017-11-22","Area_Type":"M","P_S_Name":"OMADALE TRL","D_Code":"511","P_H_Num":"","P_Price":"10000","P_Purp":"VACANT LAND","SL_Num":""}]}