{"Entries":[{"P_Area":"10.5","D_Num":"9596372","P_Sub":"THE ANGLE","P_Code":"2620","P_U_Num":"","C_Date":"2003-03-27","S_Date":"2003-05-07","Area_Type":"H","P_S_Name":"HUGS LANE","D_Code":"044","P_H_Num":"21","P_Price":"280000","P_Purp":"RURAL DWELLIN","SL_Num":""},{"P_Area":"16.49","D_Num":"AB93069","P_Sub":"THE ANGLE","P_Code":"2620","P_U_Num":"","C_Date":"2004-10-11","S_Date":"2004-11-05","Area_Type":"H","P_S_Name":"HUGS LANE","D_Code":"034","P_H_Num":"95","P_Price":"287000","P_Purp":"VACANT LAND","SL_Num":""},{"P_Area":"5111","D_Num":"AB222556","P_Sub":"THE ANGLE","P_Code":"2620","P_U_Num":"","C_Date":"2004-09-24","S_Date":"2004-09-24","Area_Type":"M","P_S_Name":"HUGS LANE","D_Code":"034","P_H_Num":"","P_Price":"3000","P_Purp":"VACANT LAND","SL_Num":""},{"P_Area":"19.37","D_Num":"AB559633","P_Sub":"THE ANGLE","P_Code":"2620","P_U_Num":"","C_Date":"2005-05-13","S_Date":"2005-06-06","Area_Type":"H","P_S_Name":"SMITHS RD","D_Code":"034","P_H_Num":"1058","P_Price":"700000","P_Purp":"RESIDENCE","SL_Num":""},{"P_Area":"127.48","D_Num":"AB307645","P_Sub":"THE ANGLE","P_Code":"2620","P_U_Num":"","C_Date":"2004-10-18","S_Date":"2005-01-12","Area_Type":"H","P_S_Name":"SMITHS RD","D_Code":"034","P_H_Num":"","P_Price":"385000","P_Purp":"VACANT LAND","SL_Num":""},{"P_Area":"15.42","D_Num":"AC663549","P_Sub":"THE ANGLE","P_Code":"2620","P_U_Num":"","C_Date":"2006-08-18","S_Date":"2006-09-29","Area_Type":"H","P_S_Name":"SMITHS RD","D_Code":"034","P_H_Num":"1302","P_Price":"590000","P_Purp":"RESIDENCE","SL_Num":""},{"P_Area":"8.66","D_Num":"AD314989","P_Sub":"THE ANGLE","P_Code":"2620","P_U_Num":"","C_Date":"2007-06-21","S_Date":"2007-07-23","Area_Type":"H","P_S_Name":"YELLOWBOX RD","D_Code":"034","P_H_Num":"206","P_Price":"625000","P_Purp":"RESIDENCE","SL_Num":""},{"P_Area":"16.61","D_Num":"AD115333","P_Sub":"THE ANGLE","P_Code":"2620","P_U_Num":"","C_Date":"2007-03-23","S_Date":"2007-04-23","Area_Type":"H","P_S_Name":"HUGS LANE","D_Code":"034","P_H_Num":"95","P_Price":"540000","P_Purp":"RESIDENCE","SL_Num":""},{"P_Area":"16.41","D_Num":"AE339864","P_Sub":"THE ANGLE","P_Code":"2620","P_U_Num":"","C_Date":"2008-11-12","S_Date":"2008-11-12","Area_Type":"H","P_S_Name":"HUGS LANE","D_Code":"034","P_H_Num":"94","P_Price":"234000","P_Purp":"RESIDENCE","SL_Num":""},{"P_Area":"80.87","D_Num":"AD976589","P_Sub":"THE ANGLE","P_Code":"2620","P_U_Num":"","C_Date":"2008-03-13","S_Date":"2008-04-24","Area_Type":"H","P_S_Name":"SMITHS RD","D_Code":"034","P_H_Num":"1240","P_Price":"840000","P_Purp":"RESIDENCE","SL_Num":""},{"P_Area":"9.1","D_Num":"AD809419","P_Sub":"THE ANGLE","P_Code":"2620","P_U_Num":"","C_Date":"2007-12-21","S_Date":"2008-02-08","Area_Type":"H","P_S_Name":"YELLOWBOX RD","D_Code":"034","P_H_Num":"222","P_Price":"685000","P_Purp":"FARM\/RURAL","SL_Num":""},{"P_Area":"9.936","D_Num":"AE279717","P_Sub":"THE ANGLE","P_Code":"2620","P_U_Num":"","C_Date":"2008-09-12","S_Date":"2008-10-10","Area_Type":"H","P_S_Name":"HUGS LANE","D_Code":"034","P_H_Num":"21","P_Price":"415000","P_Purp":"RESIDENCE","SL_Num":""},{"P_Area":"127.48","D_Num":"AF908192","P_Sub":"THE ANGLE","P_Code":"2620","P_U_Num":"","C_Date":"2010-05-18","S_Date":"2010-07-01","Area_Type":"H","P_S_Name":"SMITHS RD","D_Code":"034","P_H_Num":"873","P_Price":"750000","P_Purp":"RESIDENCE","SL_Num":""},{"P_Area":"16.61","D_Num":"AF859703","P_Sub":"THE ANGLE","P_Code":"2620","P_U_Num":"","C_Date":"2010-09-29","S_Date":"2010-10-29","Area_Type":"H","P_S_Name":"HUGS LANE","D_Code":"034","P_H_Num":"69","P_Price":"800000","P_Purp":"RESIDENCE","SL_Num":""},{"P_Area":"3.439","D_Num":"AG324334","P_Sub":"THE ANGLE","P_Code":"2620","P_U_Num":"","C_Date":"2011-03-31","S_Date":"2011-05-12","Area_Type":"H","P_S_Name":"SMITHS RD","D_Code":"034","P_H_Num":"1029","P_Price":"510000","P_Purp":"RESIDENCE","SL_Num":""},{"P_Area":"42.09","D_Num":"AG734246","P_Sub":"THE ANGLE","P_Code":"2620","P_U_Num":"","C_Date":"2011-09-16","S_Date":"2011-12-16","Area_Type":"H","P_S_Name":"SMITHS RD","D_Code":"034","P_H_Num":"1443","P_Price":"305000","P_Purp":"VACANT LAND","SL_Num":""},{"P_Area":"3.731","D_Num":"AH333404","P_Sub":"THE ANGLE","P_Code":"2620","P_U_Num":"","C_Date":"2012-09-05","S_Date":"2012-09-25","Area_Type":"H","P_S_Name":"SMITHS RD","D_Code":"034","P_H_Num":"1083","P_Price":"665000","P_Purp":"RESIDENCE","SL_Num":""},{"P_Area":"9.936","D_Num":"AH242926","P_Sub":"THE ANGLE","P_Code":"2620","P_U_Num":"","C_Date":"2012-06-29","S_Date":"2012-06-29","Area_Type":"H","P_S_Name":"HUGS LANE","D_Code":"034","P_H_Num":"21","P_Price":"550000","P_Purp":"RESIDENCE","SL_Num":""},{"P_Area":"16.61","D_Num":"AI262103","P_Sub":"THE ANGLE","P_Code":"2620","P_U_Num":"","C_Date":"2013-11-11","S_Date":"2013-12-13","Area_Type":"H","P_S_Name":"HUGS LANE","D_Code":"034","P_H_Num":"69","P_Price":"940000","P_Purp":"RESIDENCE","SL_Num":""},{"P_Area":"2.719","D_Num":"AH802390","P_Sub":"THE ANGLE","P_Code":"2620","P_U_Num":"","C_Date":"2011-03-05","S_Date":"2013-04-26","Area_Type":"H","P_S_Name":"SMITHS RD","D_Code":"034","P_H_Num":"","P_Price":"4680","P_Purp":"VACANT LAND","SL_Num":""},{"P_Area":"8.13","D_Num":"AI408688","P_Sub":"THE ANGLE","P_Code":"2620","P_U_Num":"","C_Date":"2013-12-06","S_Date":"2014-02-21","Area_Type":"H","P_S_Name":"YELLOWBOX RD","D_Code":"034","P_H_Num":"260","P_Price":"625000","P_Purp":"RESIDENCE","SL_Num":""},{"P_Area":"9.1","D_Num":"AI865487","P_Sub":"THE ANGLE","P_Code":"2620","P_U_Num":"","C_Date":"2014-08-27","S_Date":"2014-08-27","Area_Type":"H","P_S_Name":"YELLOWBOX RD","D_Code":"034","P_H_Num":"222","P_Price":"350000","P_Purp":"RESIDENCE","SL_Num":""},{"P_Area":"16.41","D_Num":"AJ205754","P_Sub":"THE ANGLE","P_Code":"2620","P_U_Num":"","C_Date":"2014-11-17","S_Date":"2014-12-17","Area_Type":"H","P_S_Name":"HUGS LANE","D_Code":"034","P_H_Num":"94","P_Price":"610000","P_Purp":"RESIDENCE","SL_Num":""},{"P_Area":"80.87","D_Num":"AJ739667","P_Sub":"THE ANGLE","P_Code":"2620","P_U_Num":"","C_Date":"2015-05-01","S_Date":"2015-08-05","Area_Type":"H","P_S_Name":"SMITHS RD","D_Code":"034","P_H_Num":"1240","P_Price":"900000","P_Purp":"RESIDENCE","SL_Num":""},{"P_Area":"62.38","D_Num":"AJ667883","P_Sub":"THE ANGLE","P_Code":"2620","P_U_Num":"","C_Date":"2015-06-01","S_Date":"2015-07-10","Area_Type":"H","P_S_Name":"SMITHS RD","D_Code":"034","P_H_Num":"1225","P_Price":"520000","P_Purp":"RESIDENCE","SL_Num":""},{"P_Area":"19.37","D_Num":"AK85016","P_Sub":"THE ANGLE","P_Code":"2620","P_U_Num":"","C_Date":"2015-07-28","S_Date":"2015-12-09","Area_Type":"H","P_S_Name":"SMITHS RD","D_Code":"034","P_H_Num":"1058","P_Price":"950000","P_Purp":"RESIDENCE","SL_Num":""},{"P_Area":"66.34","D_Num":"AK960052","P_Sub":"THE ANGLE","P_Code":"2620","P_U_Num":"","C_Date":"2016-08-31","S_Date":"2016-10-27","Area_Type":"H","P_S_Name":"SMITHS RD","D_Code":"034","P_H_Num":"","P_Price":"192500","P_Purp":"VACANT LAND","SL_Num":""},{"P_Area":"16.9","D_Num":"AM51212","P_Sub":"THE ANGLE","P_Code":"2620","P_U_Num":"","C_Date":"2016-11-16","S_Date":"2016-12-16","Area_Type":"H","P_S_Name":"CONTOUR RD","D_Code":"034","P_H_Num":"99","P_Price":"400000","P_Purp":"RESIDENCE","SL_Num":""},{"P_Area":"9.936","D_Num":"AM418208","P_Sub":"THE ANGLE","P_Code":"2620","P_U_Num":"","C_Date":"2017-03-22","S_Date":"2017-05-17","Area_Type":"H","P_S_Name":"HUGS LANE","D_Code":"034","P_H_Num":"21","P_Price":"597000","P_Purp":"RESIDENCE","SL_Num":""},{"P_Area":"16.98","D_Num":"AM801344","P_Sub":"THE ANGLE","P_Code":"2620","P_U_Num":"","C_Date":"2017-07-25","S_Date":"2017-10-06","Area_Type":"H","P_S_Name":"YELLOWBOX RD","D_Code":"034","P_H_Num":"243","P_Price":"1080000","P_Purp":"RESIDENCE","SL_Num":""},{"P_Area":"39.76","D_Num":"AQ244738","P_Sub":"THE ANGLE","P_Code":"2620","P_U_Num":"","C_Date":"2020-07-02","S_Date":"2020-07-14","Area_Type":"H","P_S_Name":"SMITHS RD","D_Code":"273","P_H_Num":"1186","P_Price":"85000","P_Purp":"FARM","SL_Num":""}]}